<?xml version="1.0" encoding="UTF-8"?>
<CATALOG>
<a><b>salivates</b></a>
<a><b>salivate</b></a>
<a><b>sanitates</b></a>
<a><b>jackanapeses</b></a>
<a><b>jackanapes</b></a>
<a><b>jailbreaker</b></a>
<a><b>jackhammer</b></a>
<a><b>jackhammers</b></a>
<a><b>jackasses</b></a>
<a><b>khanate</b></a>
<a><b>khanates</b></a>
<a><b>rainmaker</b></a>
<a><b>rainmakers</b></a>
<a><b>seaquakes</b></a>
<a><b>seaquake</b></a>
<a><b>labradorite</b></a>
<a><b>scandalousness</b></a>
<a><b>lacunae</b></a>
<a><b>lactate</b></a>
<a><b>reanalyze</b></a>
<a><b>reanalyses</b></a>
<a><b>reanalyzes</b></a>
<a><b>lagniappe</b></a>
<a><b>lagniappes</b></a>
<a><b>palmitate</b></a>
<a><b>palpitate</b></a>
<a><b>palpitates</b></a>
<a><b>malamute</b></a>
<a><b>malapert</b></a>
<a><b>palmate</b></a>
<a><b>palmature</b></a>
<a><b>malamutes</b></a>
<a><b>laboratories</b></a>
<a><b>palpate</b></a>
<a><b>palpates</b></a>
<a><b>palate</b></a>
<a><b>translate</b></a>
<a><b>palaver</b></a>
<a><b>palavers</b></a>
<a><b>palates</b></a>
<a><b>maculate</b></a>
<a><b>macrame</b></a>
<a><b>macrames</b></a>
<a><b>madrases</b></a>
<a><b>mainframe</b></a>
<a><b>mainframes</b></a>
<a><b>mahoganies</b></a>
<a><b>magnanimousness</b></a>
<a><b>magnate</b></a>
<a><b>magnates</b></a>
<a><b>microvasculature</b></a>
<a><b>microanalyses</b></a>
<a><b>maltase</b></a>
<a><b>mammae</b></a>
<a><b>mammate</b></a>
<a><b>maintainer</b></a>
<a><b>measurage</b></a>
<a><b>maintainers</b></a>
<a><b>sacrosanctness</b></a>
<a><b>seaplane</b></a>
<a><b>seaplanes</b></a>
<a><b>xanthate</b></a>
<a><b>uncompassionate</b></a>
<a><b>maltreatment</b></a>
<a><b>unarticulate</b></a>
<a><b>seascape</b></a>
<a><b>seascapes</b></a>
<a><b>playmate</b></a>
<a><b>sassafrases</b></a>
<a><b>reevaluate</b></a>
<a><b>reassimilates</b></a>
<a><b>reassimilate</b></a>
<a><b>reawake</b></a>
<a><b>raftage</b></a>
<a><b>tartare</b></a>
<a><b>tartrate</b></a>
<a><b>maculates</b></a>
<a><b>lactates</b></a>
<a><b>reevaluates</b></a>
<a><b>reawakes</b></a>
<a><b>seatmates</b></a>
<a><b>seatmate</b></a>
<a><b>scatophagies</b></a>
<a><b>playmates</b></a>
<a><b>maltreatments</b></a>
<a><b>spatulate</b></a>
<a><b>tabulable</b></a>
<a><b>tabulate</b></a>
<a><b>vacuolate</b></a>
<a><b>teaware</b></a>
<a><b>valuate</b></a>
<a><b>valvate</b></a>
<a><b>unaware</b></a>
<a><b>vaccinable</b></a>
<a><b>macabre</b></a>
<a><b>fadable</b></a>
<a><b>wadable</b></a>
<a><b>recalibrates</b></a>
<a><b>makeable</b></a>
<a><b>takeable</b></a>
</CATALOG>
