<?xml version="1.0" encoding="UTF-8"?>
<CATALOG>
<a><b>attenuations</b></a>
<a><b>nauseation</b></a>
<a><b>attenuation</b></a>
<a><b>annotative</b></a>
<a><b>quarantines</b></a>
<a><b>quarantine</b></a>
<a><b>anniversary</b></a>
<a><b>evaporations</b></a>
<a><b>evaporation</b></a>
<a><b>preparations</b></a>
<a><b>preparation</b></a>
<a><b>supersaturation</b></a>
<a><b>reparations</b></a>
<a><b>reparation</b></a>
<a><b>praetorian</b></a>
<a><b>separations</b></a>
<a><b>separation</b></a>
<a><b>aesopian</b></a>
<a><b>passionate</b></a>
<a><b>aerations</b></a>
<a><b>anorexias</b></a>
<a><b>aeration</b></a>
<a><b>anorexia</b></a>
<a><b>attestations</b></a>
<a><b>attestation</b></a>
<a><b>appertains</b></a>
<a><b>appertain</b></a>
<a><b>antiquates</b></a>
<a><b>antiquate</b></a>
<a><b>narratives</b></a>
<a><b>warranties</b></a>
<a><b>rainwears</b></a>
<a><b>narrative</b></a>
<a><b>rainwater</b></a>
<a><b>rainwear</b></a>
<a><b>seatrains</b></a>
<a><b>eurasians</b></a>
<a><b>seatrain</b></a>
<a><b>attainers</b></a>
<a><b>tearstain</b></a>
<a><b>reattains</b></a>
<a><b>intrastate</b></a>
<a><b>eurasian</b></a>
<a><b>attainer</b></a>
<a><b>reattain</b></a>
<a><b>sanitates</b></a>
<a><b>astatines</b></a>
<a><b>astatine</b></a>
<a><b>appropriates</b></a>
<a><b>appropriate</b></a>
<a><b>expatiators</b></a>
<a><b>expatiator</b></a>
<a><b>apostasies</b></a>
<a><b>apostatizes</b></a>
<a><b>apostatize</b></a>
<a><b>appraiser</b></a>
<a><b>appraisers</b></a>
<a><b>appraise</b></a>
<a><b>appraises</b></a>
<a><b>spiraea</b></a>
<a><b>spiraeas</b></a>
<a><b>separatists</b></a>
<a><b>satrapies</b></a>
<a><b>aspirates</b></a>
<a><b>parasites</b></a>
<a><b>separatist</b></a>
<a><b>aspirate</b></a>
<a><b>parasite</b></a>
<a><b>apatites</b></a>
<a><b>apatite</b></a>
<a><b>terraria</b></a>
<a><b>satyriases</b></a>
<a><b>statuaries</b></a>
<a><b>variates</b></a>
<a><b>awaiters</b></a>
<a><b>eurasia</b></a>
<a><b>airwaves</b></a>
<a><b>awaiter</b></a>
<a><b>airwave</b></a>
<a><b>assuasive</b></a>
<a><b>satiates</b></a>
<a><b>satiate</b></a>
<a><b>aviates</b></a>
<a><b>aviate</b></a>
<a><b>jaywalkers</b></a>
<a><b>jaywalker</b></a>
<a><b>japanner</b></a>
<a><b>japanners</b></a>
<a><b>kayakers</b></a>
<a><b>kayaker</b></a>
<a><b>lawmakers</b></a>
<a><b>malarkeys</b></a>
<a><b>lawmaker</b></a>
<a><b>malarkey</b></a>
<a><b>mapmaker</b></a>
<a><b>mapmakers</b></a>
<a><b>keratomas</b></a>
<a><b>earmark</b></a>
<a><b>earmarks</b></a>
<a><b>watermarks</b></a>
</CATALOG>
