<?xml version="1.0" encoding="UTF-8"?>
<CATALOG>
<a><b>beaklike</b></a>
<a><b>beanlike</b></a>
<a><b>bakeries</b></a>
<a><b>beakless</b></a>
<a><b>beaker</b></a>
<a><b>beakers</b></a>
<a><b>beefsteaks</b></a>
<a><b>beefsteak</b></a>
<a><b>betake</b></a>
<a><b>balinese</b></a>
<a><b>beamless</b></a>
<a><b>baleen</b></a>
<a><b>baleens</b></a>
<a><b>ableness</b></a>
<a><b>beleaps</b></a>
<a><b>beleapt</b></a>
<a><b>baseless</b></a>
<a><b>barometer</b></a>
<a><b>barometers</b></a>
<a><b>beanpole</b></a>
<a><b>beanpoles</b></a>
<a><b>baronesses</b></a>
<a><b>bareness</b></a>
<a><b>beanery</b></a>
<a><b>baseness</b></a>
<a><b>seborrhea</b></a>
<a><b>aerobe</b></a>
<a><b>aerobes</b></a>
<a><b>behaver</b></a>
<a><b>bearer</b></a>
<a><b>bearers</b></a>
<a><b>barrette</b></a>
<a><b>barrettes</b></a>
<a><b>berrettas</b></a>
<a><b>berate</b></a>
<a><b>beretta</b></a>
<a><b>beware</b></a>
<a><b>breezeways</b></a>
<a><b>beeswaxes</b></a>
<a><b>behavers</b></a>
<a><b>behaves</b></a>
<a><b>beastliness</b></a>
<a><b>beastliest</b></a>
<a><b>beasties</b></a>
<a><b>beastie</b></a>
<a><b>berates</b></a>
<a><b>berettas</b></a>
<a><b>beeswax</b></a>
<a><b>bathysphere</b></a>
<a><b>breezeway</b></a>
<a><b>baffle</b></a>
<a><b>baffler</b></a>
<a><b>bafflers</b></a>
<a><b>baffles</b></a>
<a><b>befalling</b></a>
<a><b>bashfulness</b></a>
<a><b>basifies</b></a>
<a><b>lifeboats</b></a>
<a><b>lifeboat</b></a>
<a><b>barflies</b></a>
<a><b>beautify</b></a>
<a><b>beatify</b></a>
<a><b>befall</b></a>
<a><b>befalls</b></a>
<a><b>belfast</b></a>
<a><b>february</b></a>
<a><b>abridge</b></a>
<a><b>abridger</b></a>
<a><b>abridgers</b></a>
<a><b>abridges</b></a>
<a><b>beavering</b></a>
<a><b>baguette</b></a>
<a><b>beatifying</b></a>
<a><b>beflags</b></a>
<a><b>beggaring</b></a>
<a><b>baggie</b></a>
<a><b>bagginess</b></a>
<a><b>baggier</b></a>
<a><b>baggies</b></a>
<a><b>baggiest</b></a>
<a><b>beggarly</b></a>
<a><b>beggar</b></a>
<a><b>beggars</b></a>
<a><b>beggary</b></a>
<a><b>belgian</b></a>
<a><b>belgians</b></a>
<a><b>beaming</b></a>
<a><b>beaning</b></a>
<a><b>benignant</b></a>
<a><b>begonia</b></a>
<a><b>begonias</b></a>
<a><b>bearing</b></a>
<a><b>bearings</b></a>
<a><b>beating</b></a>
<a><b>bagpipe</b></a>
<a><b>bagpiper</b></a>
<a><b>bagpipers</b></a>
<a><b>bagpipes</b></a>
<a><b>bagel</b></a>
<a><b>bangle</b></a>
</CATALOG>
