<?xml version="1.0" encoding="UTF-8"?>
<CATALOG>
<a><b>enchantment</b></a>
<a><b>trencherman</b></a>
<a><b>rapprochements</b></a>
<a><b>rapprochement</b></a>
<a><b>preachments</b></a>
<a><b>preachment</b></a>
<a><b>menarche</b></a>
<a><b>menarches</b></a>
<a><b>manchester</b></a>
<a><b>archenemy</b></a>
<a><b>tachometers</b></a>
<a><b>overmatches</b></a>
<a><b>tachometer</b></a>
<a><b>machree</b></a>
<a><b>machrees</b></a>
<a><b>cashmere</b></a>
<a><b>cashmeres</b></a>
<a><b>rematches</b></a>
<a><b>machetes</b></a>
<a><b>machete</b></a>
<a><b>achene</b></a>
<a><b>enhance</b></a>
<a><b>enhancer</b></a>
<a><b>enhancers</b></a>
<a><b>enchantress</b></a>
<a><b>enchanters</b></a>
<a><b>enchanter</b></a>
<a><b>enhances</b></a>
<a><b>unchasteness</b></a>
<a><b>anchoresses</b></a>
<a><b>cheapen</b></a>
<a><b>cheapens</b></a>
<a><b>cheapness</b></a>
<a><b>chasteners</b></a>
<a><b>chastener</b></a>
<a><b>achenes</b></a>
<a><b>chasteness</b></a>
<a><b>chanteuses</b></a>
<a><b>chanteuse</b></a>
<a><b>sharecropper</b></a>
<a><b>sharecroppers</b></a>
<a><b>reproacher</b></a>
<a><b>reproaches</b></a>
<a><b>racehorse</b></a>
<a><b>racehorses</b></a>
<a><b>orchestrates</b></a>
<a><b>orchestrate</b></a>
<a><b>treacherous</b></a>
<a><b>overarches</b></a>
<a><b>overreach</b></a>
<a><b>outreaches</b></a>
<a><b>peacher</b></a>
<a><b>cheaper</b></a>
<a><b>preacher</b></a>
<a><b>preachers</b></a>
<a><b>repurchases</b></a>
<a><b>repurchase</b></a>
<a><b>preaches</b></a>
<a><b>archetypes</b></a>
<a><b>upreaches</b></a>
<a><b>archetype</b></a>
<a><b>peaches</b></a>
<a><b>cheapest</b></a>
<a><b>reacher</b></a>
<a><b>charterers</b></a>
<a><b>recharters</b></a>
<a><b>charterer</b></a>
<a><b>recharter</b></a>
<a><b>searcher</b></a>
<a><b>reachers</b></a>
<a><b>research</b></a>
<a><b>searchers</b></a>
<a><b>chatterers</b></a>
<a><b>chartreuse</b></a>
<a><b>chatterer</b></a>
<a><b>treachery</b></a>
<a><b>reaches</b></a>
<a><b>searches</b></a>
<a><b>teachers</b></a>
<a><b>hectares</b></a>
<a><b>cheaters</b></a>
<a><b>catheters</b></a>
<a><b>hectare</b></a>
<a><b>teacher</b></a>
<a><b>reteach</b></a>
<a><b>cheater</b></a>
<a><b>catheter</b></a>
<a><b>cheatery</b></a>
<a><b>teaches</b></a>
<a><b>cathexes</b></a>
<a><b>illiteracies</b></a>
<a><b>sociosexualities</b></a>
<a><b>equivocalities</b></a>
<a><b>peculiarities</b></a>
<a><b>elasticities</b></a>
<a><b>recriminative</b></a>
<a><b>insurrectionaries</b></a>
<a><b>antisepticize</b></a>
<a><b>acquisitiveness</b></a>
<a><b>reactivities</b></a>
</CATALOG>
