<?xml version="1.0" encoding="UTF-8"?>
<CATALOG>
<a><b>aches</b></a>
<a><b>bellyaches</b></a>
<a><b>schizophrenia</b></a>
<a><b>cashes</b></a>
<a><b>cashews</b></a>
<a><b>cheats</b></a>
<a><b>cashew</b></a>
<a><b>cheat</b></a>
<a><b>aerobatics</b></a>
<a><b>aeronautic</b></a>
<a><b>aeronautics</b></a>
<a><b>aerodynamic</b></a>
<a><b>aerodynamics</b></a>
<a><b>aerobic</b></a>
<a><b>aerobics</b></a>
<a><b>carnegie</b></a>
<a><b>canneries</b></a>
<a><b>causerie</b></a>
<a><b>cauterize</b></a>
<a><b>cassiterite</b></a>
<a><b>athletic</b></a>
<a><b>chelation</b></a>
<a><b>acrimonies</b></a>
<a><b>acrimoniousness</b></a>
<a><b>cakier</b></a>
<a><b>cakiest</b></a>
<a><b>carillonneur</b></a>
<a><b>carillonneurs</b></a>
<a><b>collinear</b></a>
<a><b>calliope</b></a>
<a><b>calliopes</b></a>
<a><b>calliper</b></a>
<a><b>cliental</b></a>
<a><b>colinear</b></a>
<a><b>callosities</b></a>
<a><b>cariole</b></a>
<a><b>replica</b></a>
<a><b>caliper</b></a>
<a><b>replicas</b></a>
<a><b>calipers</b></a>
<a><b>camisole</b></a>
<a><b>camisoles</b></a>
<a><b>anemic</b></a>
<a><b>iceman</b></a>
<a><b>carmine</b></a>
<a><b>carmines</b></a>
<a><b>crimea</b></a>
<a><b>chemotherapists</b></a>
<a><b>chemotherapist</b></a>
<a><b>cannie</b></a>
<a><b>canine</b></a>
<a><b>canniness</b></a>
<a><b>cannier</b></a>
<a><b>canines</b></a>
<a><b>canniest</b></a>
<a><b>aeonic</b></a>
<a><b>caponize</b></a>
<a><b>veronica</b></a>
<a><b>caponizes</b></a>
<a><b>aconite</b></a>
<a><b>carnie</b></a>
<a><b>carnivore</b></a>
<a><b>carnies</b></a>
<a><b>carnivorousness</b></a>
<a><b>carnivores</b></a>
<a><b>aconites</b></a>
<a><b>acropolises</b></a>
<a><b>carrotier</b></a>
<a><b>carrotiest</b></a>
<a><b>ceria</b></a>
<a><b>carrier</b></a>
<a><b>carriers</b></a>
<a><b>carries</b></a>
<a><b>cerias</b></a>
<a><b>caries</b></a>
<a><b>canisters</b></a>
<a><b>canister</b></a>
<a><b>aseptic</b></a>
<a><b>active</b></a>
<a><b>cavie</b></a>
<a><b>adjunctive</b></a>
<a><b>cajoleries</b></a>
<a><b>cajole</b></a>
<a><b>cajoler</b></a>
<a><b>cajolers</b></a>
<a><b>cajolery</b></a>
<a><b>cajoles</b></a>
<a><b>cake</b></a>
<a><b>catlike</b></a>
<a><b>calker</b></a>
<a><b>calkers</b></a>
<a><b>acknowledge</b></a>
<a><b>cankerous</b></a>
<a><b>canker</b></a>
<a><b>acknowledger</b></a>
<a><b>cankers</b></a>
<a><b>acknowledgements</b></a>
<a><b>acknowledgments</b></a>
<a><b>acknowledgers</b></a>
<a><b>acknowledges</b></a>
</CATALOG>
