<?xml version="1.0" encoding="UTF-8"?>
<CATALOG>
<a><b>saucer</b></a>
<a><b>causer</b></a>
<a><b>cesura</b></a>
<a><b>cavers</b></a>
<a><b>carves</b></a>
<a><b>craves</b></a>
<a><b>scarey</b></a>
<a><b>creasy</b></a>
<a><b>crazes</b></a>
<a><b>crate</b></a>
<a><b>trace</b></a>
<a><b>caret</b></a>
<a><b>recta</b></a>
<a><b>react</b></a>
<a><b>carte</b></a>
<a><b>cater</b></a>
<a><b>extract</b></a>
<a><b>curate</b></a>
<a><b>acuter</b></a>
<a><b>cautery</b></a>
<a><b>crave</b></a>
<a><b>caver</b></a>
<a><b>carve</b></a>
<a><b>craze</b></a>
<a><b>aces</b></a>
<a><b>case</b></a>
<a><b>cases</b></a>
<a><b>castes</b></a>
<a><b>cuestas</b></a>
<a><b>ecstasy</b></a>
<a><b>sauces</b></a>
<a><b>causes</b></a>
<a><b>cayuses</b></a>
<a><b>causeys</b></a>
<a><b>caste</b></a>
<a><b>cates</b></a>
<a><b>acutest</b></a>
<a><b>testacy</b></a>
<a><b>cuesta</b></a>
<a><b>acutes</b></a>
<a><b>exacts</b></a>
<a><b>aztecs</b></a>
<a><b>cause</b></a>
<a><b>sauce</b></a>
<a><b>cayuse</b></a>
<a><b>caves</b></a>
<a><b>tacet</b></a>
<a><b>acute</b></a>
<a><b>exact</b></a>
<a><b>aztec</b></a>
<a><b>cave</b></a>
<a><b>cliffhanging</b></a>
<a><b>chaffing</b></a>
<a><b>officiating</b></a>
<a><b>trafficking</b></a>
<a><b>afflicting</b></a>
<a><b>suffocatingly</b></a>
<a><b>suffocating</b></a>
<a><b>chaff</b></a>
<a><b>chaffs</b></a>
<a><b>chaffy</b></a>
<a><b>officialism</b></a>
<a><b>inofficial</b></a>
<a><b>officiality</b></a>
<a><b>fortifications</b></a>
<a><b>fortification</b></a>
<a><b>officiation</b></a>
<a><b>nonofficially</b></a>
<a><b>unofficially</b></a>
<a><b>officially</b></a>
<a><b>nonofficial</b></a>
<a><b>officinal</b></a>
<a><b>afflictions</b></a>
<a><b>affliction</b></a>
<a><b>unofficial</b></a>
<a><b>official</b></a>
<a><b>officials</b></a>
<a><b>officiants</b></a>
<a><b>officiant</b></a>
<a><b>officiator</b></a>
<a><b>officiary</b></a>
<a><b>caitiffs</b></a>
<a><b>caitiff</b></a>
<a><b>trafficks</b></a>
<a><b>traffick</b></a>
<a><b>fancifully</b></a>
<a><b>fanciful</b></a>
<a><b>afflicts</b></a>
<a><b>afflict</b></a>
<a><b>suffocation</b></a>
<a><b>traffics</b></a>
<a><b>traffic</b></a>
<a><b>offtrack</b></a>
<a><b>scofflaws</b></a>
<a><b>scofflaw</b></a>
<a><b>factful</b></a>
<a><b>castoffs</b></a>
<a><b>offcast</b></a>
<a><b>castoff</b></a>
<a><b>franchising</b></a>
</CATALOG>
