<?xml version="1.0" encoding="UTF-8"?>
<CATALOG>
<a><b>drawn</b></a>
<a><b>randy</b></a>
<a><b>ands</b></a>
<a><b>sand</b></a>
<a><b>sands</b></a>
<a><b>stands</b></a>
<a><b>datsuns</b></a>
<a><b>dynasts</b></a>
<a><b>sundays</b></a>
<a><b>stand</b></a>
<a><b>daunts</b></a>
<a><b>datsun</b></a>
<a><b>dynast</b></a>
<a><b>dynasty</b></a>
<a><b>sudan</b></a>
<a><b>sunday</b></a>
<a><b>wands</b></a>
<a><b>dawns</b></a>
<a><b>sandy</b></a>
<a><b>daunt</b></a>
<a><b>dawn</b></a>
<a><b>wand</b></a>
<a><b>ado</b></a>
<a><b>trapdoors</b></a>
<a><b>trapdoor</b></a>
<a><b>sauropods</b></a>
<a><b>sauropod</b></a>
<a><b>sapwoods</b></a>
<a><b>sapwood</b></a>
<a><b>doorways</b></a>
<a><b>doorway</b></a>
<a><b>woodwax</b></a>
<a><b>passwords</b></a>
<a><b>password</b></a>
<a><b>parody</b></a>
<a><b>soapsuds</b></a>
<a><b>adopts</b></a>
<a><b>adopt</b></a>
<a><b>road</b></a>
<a><b>ardor</b></a>
<a><b>ardors</b></a>
<a><b>wordstar</b></a>
<a><b>ardours</b></a>
<a><b>ardour</b></a>
<a><b>sarod</b></a>
<a><b>roads</b></a>
<a><b>dorsa</b></a>
<a><b>outwards</b></a>
<a><b>towards</b></a>
<a><b>arduous</b></a>
<a><b>tardo</b></a>
<a><b>outward</b></a>
<a><b>outdraw</b></a>
<a><b>toward</b></a>
<a><b>soda</b></a>
<a><b>ados</b></a>
<a><b>sodas</b></a>
<a><b>toads</b></a>
<a><b>todays</b></a>
<a><b>woads</b></a>
<a><b>toad</b></a>
<a><b>today</b></a>
<a><b>toady</b></a>
<a><b>woad</b></a>
<a><b>pad</b></a>
<a><b>pard</b></a>
<a><b>purdas</b></a>
<a><b>upwards</b></a>
<a><b>upward</b></a>
<a><b>pads</b></a>
<a><b>avdp</b></a>
<a><b>squads</b></a>
<a><b>quads</b></a>
<a><b>squad</b></a>
<a><b>quad</b></a>
<a><b>rad</b></a>
<a><b>durra</b></a>
<a><b>rads</b></a>
<a><b>stardusts</b></a>
<a><b>stardust</b></a>
<a><b>swards</b></a>
<a><b>darts</b></a>
<a><b>drats</b></a>
<a><b>wards</b></a>
<a><b>sward</b></a>
<a><b>draws</b></a>
<a><b>yards</b></a>
<a><b>drays</b></a>
<a><b>dart</b></a>
<a><b>drat</b></a>
<a><b>tawdry</b></a>
<a><b>tardy</b></a>
<a><b>ward</b></a>
<a><b>draw</b></a>
<a><b>yard</b></a>
<a><b>dray</b></a>
<a><b>ads</b></a>
<a><b>sad</b></a>
<a><b>sawdusts</b></a>
<a><b>sawdust</b></a>
</CATALOG>
