<?xml version="1.0" encoding="UTF-8"?>
<CATALOG>
<a><b>raving</b></a>
<a><b>varying</b></a>
<a><b>waring</b></a>
<a><b>grainy</b></a>
<a><b>raying</b></a>
<a><b>razing</b></a>
<a><b>razzing</b></a>
<a><b>gains</b></a>
<a><b>assign</b></a>
<a><b>sassing</b></a>
<a><b>assigns</b></a>
<a><b>savings</b></a>
<a><b>sayings</b></a>
<a><b>giants</b></a>
<a><b>gainst</b></a>
<a><b>sating</b></a>
<a><b>tasting</b></a>
<a><b>stating</b></a>
<a><b>tattings</b></a>
<a><b>statuting</b></a>
<a><b>swatting</b></a>
<a><b>staving</b></a>
<a><b>wasting</b></a>
<a><b>stygian</b></a>
<a><b>staying</b></a>
<a><b>saving</b></a>
<a><b>savvying</b></a>
<a><b>sawing</b></a>
<a><b>waxwings</b></a>
<a><b>waxings</b></a>
<a><b>swaying</b></a>
<a><b>saying</b></a>
<a><b>giant</b></a>
<a><b>tatting</b></a>
<a><b>tauting</b></a>
<a><b>vatting</b></a>
<a><b>tawing</b></a>
<a><b>taxing</b></a>
<a><b>taxying</b></a>
<a><b>waving</b></a>
<a><b>awing</b></a>
<a><b>waxwing</b></a>
<a><b>waxing</b></a>
<a><b>yawing</b></a>
<a><b>axing</b></a>
<a><b>autogiros</b></a>
<a><b>grazioso</b></a>
<a><b>autogiro</b></a>
<a><b>agitprops</b></a>
<a><b>agitprop</b></a>
<a><b>gaposis</b></a>
<a><b>gratuitous</b></a>
<a><b>viragos</b></a>
<a><b>virago</b></a>
<a><b>agouti</b></a>
<a><b>gratis</b></a>
<a><b>guitars</b></a>
<a><b>gratuity</b></a>
<a><b>guitar</b></a>
<a><b>gravity</b></a>
<a><b>agists</b></a>
<a><b>gaits</b></a>
<a><b>agist</b></a>
<a><b>gait</b></a>
<a><b>jag</b></a>
<a><b>logjam</b></a>
<a><b>logjams</b></a>
<a><b>jangly</b></a>
<a><b>jugulars</b></a>
<a><b>jugular</b></a>
<a><b>jugula</b></a>
<a><b>jargon</b></a>
<a><b>jargons</b></a>
<a><b>jags</b></a>
<a><b>glasswork</b></a>
<a><b>sparkplug</b></a>
<a><b>kymograms</b></a>
<a><b>gasworks</b></a>
<a><b>skag</b></a>
<a><b>skags</b></a>
<a><b>gawks</b></a>
<a><b>gawk</b></a>
<a><b>gawky</b></a>
<a><b>gal</b></a>
<a><b>lag</b></a>
<a><b>gall</b></a>
<a><b>polygonally</b></a>
<a><b>glamorously</b></a>
<a><b>gallon</b></a>
<a><b>polygonal</b></a>
<a><b>languorously</b></a>
<a><b>gallons</b></a>
<a><b>gallnuts</b></a>
<a><b>galloots</b></a>
<a><b>galloot</b></a>
<a><b>gallop</b></a>
<a><b>gallops</b></a>
<a><b>garrulously</b></a>
<a><b>glossal</b></a>
<a><b>gallows</b></a>
</CATALOG>
