<?xml version="1.0" encoding="UTF-8"?>
<CATALOG>
<a><b>audibles</b></a>
<a><b>eyebeams</b></a>
<a><b>subgenera</b></a>
<a><b>auberges</b></a>
<a><b>eyeballs</b></a>
<a><b>rubellas</b></a>
<a><b>byelorussians</b></a>
<a><b>buenas</b></a>
<a><b>bureaus</b></a>
<a><b>buffalos</b></a>
<a><b>burglars</b></a>
<a><b>suburbia</b></a>
<a><b>bucktails</b></a>
<a><b>bulimias</b></a>
<a><b>nubias</b></a>
<a><b>subphyla</b></a>
<a><b>byplays</b></a>
<a><b>bylaws</b></a>
<a><b>rumbas</b></a>
<a><b>lubricants</b></a>
<a><b>subpoenas</b></a>
<a><b>subpoena</b></a>
<a><b>subpenas</b></a>
<a><b>subpena</b></a>
<a><b>hybridizations</b></a>
<a><b>auburns</b></a>
<a><b>lubricators</b></a>
<a><b>overbears</b></a>
<a><b>autobus</b></a>
<a><b>bypass</b></a>
<a><b>bursars</b></a>
<a><b>bursas</b></a>
<a><b>suburbias</b></a>
<a><b>subways</b></a>
<a><b>subway</b></a>
<a><b>byways</b></a>
<a><b>autodidacts</b></a>
<a><b>audacities</b></a>
<a><b>audaciousness</b></a>
<a><b>audacious</b></a>
<a><b>czechoslovakians</b></a>
<a><b>sugarcoats</b></a>
<a><b>attracts</b></a>
<a><b>cutaways</b></a>
<a><b>cudbears</b></a>
<a><b>cyclecars</b></a>
<a><b>cycads</b></a>
<a><b>czechoslovaks</b></a>
<a><b>cyclopedias</b></a>
<a><b>mudcaps</b></a>
<a><b>ducats</b></a>
<a><b>excommunicators</b></a>
<a><b>cyclamens</b></a>
<a><b>audiences</b></a>
<a><b>cyanides</b></a>
<a><b>excommunicates</b></a>
<a><b>etceteras</b></a>
<a><b>execrates</b></a>
<a><b>excogitates</b></a>
<a><b>exchanges</b></a>
<a><b>exclaimers</b></a>
<a><b>exculpates</b></a>
<a><b>exclaves</b></a>
<a><b>eucalyptuses</b></a>
<a><b>eucharists</b></a>
<a><b>nucleators</b></a>
<a><b>eucalyptus</b></a>
<a><b>execrations</b></a>
<a><b>excitations</b></a>
<a><b>excitants</b></a>
<a><b>cyanoses</b></a>
<a><b>excoriates</b></a>
<a><b>execrators</b></a>
<a><b>cuestas</b></a>
<a><b>aztecs</b></a>
<a><b>fuchsias</b></a>
<a><b>athletics</b></a>
<a><b>automatics</b></a>
<a><b>exclaims</b></a>
<a><b>avionics</b></a>
<a><b>ducktails</b></a>
<a><b>atomics</b></a>
<a><b>exemplifications</b></a>
<a><b>cyanosis</b></a>
<a><b>atonics</b></a>
<a><b>czarists</b></a>
<a><b>cuirass</b></a>
<a><b>attics</b></a>
<a><b>hydrocephalus</b></a>
<a><b>cupolas</b></a>
<a><b>culpas</b></a>
<a><b>cutlas</b></a>
<a><b>czardoms</b></a>
<a><b>cumshaws</b></a>
<a><b>czarisms</b></a>
<a><b>atmospherics</b></a>
<a><b>cumquats</b></a>
<a><b>hydrotherapeuticians</b></a>
<a><b>excommunications</b></a>
<a><b>exculpations</b></a>
</CATALOG>
