<?xml version="1.0" encoding="UTF-8"?>
<CATALOG>
<a><b>hesitates</b></a>
<a><b>hepatizes</b></a>
<a><b>hesitate</b></a>
<a><b>hematologies</b></a>
<a><b>halflife</b></a>
<a><b>hangfire</b></a>
<a><b>halflives</b></a>
<a><b>halftime</b></a>
<a><b>halftone</b></a>
<a><b>halfpenny</b></a>
<a><b>halftimes</b></a>
<a><b>halftones</b></a>
<a><b>haulage</b></a>
<a><b>hermitage</b></a>
<a><b>hermitages</b></a>
<a><b>hangmen</b></a>
<a><b>hallucinogen</b></a>
<a><b>hanger</b></a>
<a><b>hangover</b></a>
<a><b>hangers</b></a>
<a><b>hangovers</b></a>
<a><b>heritage</b></a>
<a><b>hallucinogens</b></a>
<a><b>heritages</b></a>
<a><b>hashishes</b></a>
<a><b>thallophyte</b></a>
<a><b>hashes</b></a>
<a><b>hairbrushes</b></a>
<a><b>hairpiece</b></a>
<a><b>hairpieces</b></a>
<a><b>haircutter</b></a>
<a><b>hairdresser</b></a>
<a><b>hairdressers</b></a>
<a><b>hellgrammite</b></a>
<a><b>hellgrammites</b></a>
<a><b>hairlessness</b></a>
<a><b>sailfishes</b></a>
<a><b>philanthropies</b></a>
<a><b>hairline</b></a>
<a><b>hairlines</b></a>
<a><b>thiamine</b></a>
<a><b>hairiness</b></a>
<a><b>hairier</b></a>
<a><b>hairiest</b></a>
<a><b>hairlike</b></a>
<a><b>hankie</b></a>
<a><b>hankies</b></a>
<a><b>shakiness</b></a>
<a><b>shakiest</b></a>
<a><b>hallucinative</b></a>
<a><b>hailer</b></a>
<a><b>hailers</b></a>
<a><b>hairless</b></a>
<a><b>hailstones</b></a>
<a><b>hailstone</b></a>
<a><b>harlotries</b></a>
<a><b>halite</b></a>
<a><b>hammier</b></a>
<a><b>shammies</b></a>
<a><b>hammiest</b></a>
<a><b>harmonizer</b></a>
<a><b>harmonies</b></a>
<a><b>harmonize</b></a>
<a><b>harmonizers</b></a>
<a><b>harmonizes</b></a>
<a><b>shipmates</b></a>
<a><b>shipmate</b></a>
<a><b>harmoniousness</b></a>
<a><b>wahine</b></a>
<a><b>thiosulfate</b></a>
<a><b>shipshape</b></a>
<a><b>happier</b></a>
<a><b>happiest</b></a>
<a><b>harpies</b></a>
<a><b>sharpie</b></a>
<a><b>sharpies</b></a>
<a><b>triphase</b></a>
<a><b>hairweaver</b></a>
<a><b>hairsplitter</b></a>
<a><b>hairsplitters</b></a>
<a><b>rakishness</b></a>
<a><b>harrier</b></a>
<a><b>harriers</b></a>
<a><b>harries</b></a>
<a><b>harriet</b></a>
<a><b>hairstyles</b></a>
<a><b>hairstyle</b></a>
<a><b>hairweavers</b></a>
<a><b>paintbrushes</b></a>
<a><b>hallucinoses</b></a>
<a><b>halitoses</b></a>
<a><b>shanties</b></a>
<a><b>jailhouse</b></a>
<a><b>hajjes</b></a>
<a><b>hake</b></a>
<a><b>hektare</b></a>
<a><b>hawknose</b></a>
<a><b>hanker</b></a>
<a><b>hankers</b></a>
<a><b>shakoes</b></a>
</CATALOG>
