<?xml version="1.0" encoding="UTF-8"?>
<CATALOG>
<a><b>regrooves</b></a>
<a><b>ogees</b></a>
<a><b>gessoes</b></a>
<a><b>yogee</b></a>
<a><b>expunge</b></a>
<a><b>genteeler</b></a>
<a><b>gentler</b></a>
<a><b>regress</b></a>
<a><b>regrets</b></a>
<a><b>regret</b></a>
<a><b>regrew</b></a>
<a><b>reges</b></a>
<a><b>serge</b></a>
<a><b>egress</b></a>
<a><b>serges</b></a>
<a><b>egrets</b></a>
<a><b>egret</b></a>
<a><b>verge</b></a>
<a><b>gees</b></a>
<a><b>genteelness</b></a>
<a><b>genteelest</b></a>
<a><b>genuineness</b></a>
<a><b>gentleness</b></a>
<a><b>festering</b></a>
<a><b>gentiles</b></a>
<a><b>vestige</b></a>
<a><b>legumes</b></a>
<a><b>gentles</b></a>
<a><b>gentlest</b></a>
<a><b>gentries</b></a>
<a><b>genuses</b></a>
<a><b>neguses</b></a>
<a><b>gestes</b></a>
<a><b>segues</b></a>
<a><b>geste</b></a>
<a><b>gestures</b></a>
<a><b>gesture</b></a>
<a><b>segue</b></a>
<a><b>hee</b></a>
<a><b>trochee</b></a>
<a><b>whiffletree</b></a>
<a><b>heterophile</b></a>
<a><b>hellene</b></a>
<a><b>hellenes</b></a>
<a><b>hemisphere</b></a>
<a><b>hemispheres</b></a>
<a><b>telephone</b></a>
<a><b>enmeshments</b></a>
<a><b>enmeshment</b></a>
<a><b>enmeshes</b></a>
<a><b>herpeses</b></a>
<a><b>heretofore</b></a>
<a><b>heresies</b></a>
<a><b>somewhere</b></a>
<a><b>shoetrees</b></a>
<a><b>shoetree</b></a>
<a><b>selfishness</b></a>
<a><b>heifer</b></a>
<a><b>heifers</b></a>
<a><b>feverish</b></a>
<a><b>shiftlessness</b></a>
<a><b>heighten</b></a>
<a><b>heightens</b></a>
<a><b>enlighten</b></a>
<a><b>enlightens</b></a>
<a><b>hellishness</b></a>
<a><b>hellhole</b></a>
<a><b>hellholes</b></a>
<a><b>henhouse</b></a>
<a><b>henhouses</b></a>
<a><b>herewith</b></a>
<a><b>philanderer</b></a>
<a><b>philanderers</b></a>
<a><b>replenisher</b></a>
<a><b>replenishers</b></a>
<a><b>replenishes</b></a>
<a><b>whippletree</b></a>
<a><b>epinephrine</b></a>
<a><b>henneries</b></a>
<a><b>heiresses</b></a>
<a><b>hellfire</b></a>
<a><b>hellfires</b></a>
<a><b>heinie</b></a>
<a><b>heinies</b></a>
<a><b>hemline</b></a>
<a><b>hemlines</b></a>
<a><b>relinquisher</b></a>
<a><b>relinquishers</b></a>
<a><b>relinquishes</b></a>
<a><b>philoprogenitive</b></a>
<a><b>heliotrope</b></a>
<a><b>heirless</b></a>
<a><b>heliotropes</b></a>
<a><b>thermite</b></a>
<a><b>rhinoceroses</b></a>
<a><b>rhinestones</b></a>
<a><b>rhinestone</b></a>
<a><b>heinousness</b></a>
<a><b>eohippuses</b></a>
<a><b>theorize</b></a>
</CATALOG>
