<?xml version="1.0" encoding="UTF-8"?>
<CATALOG>
<a><b>kremlins</b></a>
<a><b>irksomely</b></a>
<a><b>milker</b></a>
<a><b>milkers</b></a>
<a><b>inkle</b></a>
<a><b>liken</b></a>
<a><b>unwrinkles</b></a>
<a><b>unwrinkle</b></a>
<a><b>plinker</b></a>
<a><b>sprinkler</b></a>
<a><b>sprinklers</b></a>
<a><b>sprinkle</b></a>
<a><b>sprinkles</b></a>
<a><b>linker</b></a>
<a><b>knurlier</b></a>
<a><b>linkers</b></a>
<a><b>knurliest</b></a>
<a><b>twinklers</b></a>
<a><b>wrinkles</b></a>
<a><b>twinkler</b></a>
<a><b>wrinkle</b></a>
<a><b>likens</b></a>
<a><b>inkles</b></a>
<a><b>silken</b></a>
<a><b>inkless</b></a>
<a><b>kinless</b></a>
<a><b>skinless</b></a>
<a><b>sulkiness</b></a>
<a><b>skylines</b></a>
<a><b>tinkles</b></a>
<a><b>twinkles</b></a>
<a><b>kelvins</b></a>
<a><b>welkins</b></a>
<a><b>winkles</b></a>
<a><b>skyline</b></a>
<a><b>tinkle</b></a>
<a><b>nutlike</b></a>
<a><b>twinkle</b></a>
<a><b>unlike</b></a>
<a><b>kelvin</b></a>
<a><b>welkin</b></a>
<a><b>winkle</b></a>
<a><b>rootlike</b></a>
<a><b>kryolites</b></a>
<a><b>yolkier</b></a>
<a><b>perkily</b></a>
<a><b>puslike</b></a>
<a><b>peskily</b></a>
<a><b>liker</b></a>
<a><b>likers</b></a>
<a><b>kirtles</b></a>
<a><b>kilters</b></a>
<a><b>sulkier</b></a>
<a><b>kirtle</b></a>
<a><b>kilter</b></a>
<a><b>klutzier</b></a>
<a><b>likes</b></a>
<a><b>skittles</b></a>
<a><b>sulkiest</b></a>
<a><b>sulkies</b></a>
<a><b>likest</b></a>
<a><b>skittle</b></a>
<a><b>klutziest</b></a>
<a><b>kevils</b></a>
<a><b>mike</b></a>
<a><b>skimmer</b></a>
<a><b>skimmers</b></a>
<a><b>kinswomen</b></a>
<a><b>kinsmen</b></a>
<a><b>moniker</b></a>
<a><b>monikers</b></a>
<a><b>smokiness</b></a>
<a><b>tokenisms</b></a>
<a><b>tokenism</b></a>
<a><b>murkiness</b></a>
<a><b>muskiness</b></a>
<a><b>misspoke</b></a>
<a><b>smokier</b></a>
<a><b>irksome</b></a>
<a><b>timeworks</b></a>
<a><b>timework</b></a>
<a><b>eskimo</b></a>
<a><b>eskimos</b></a>
<a><b>smokiest</b></a>
<a><b>smirker</b></a>
<a><b>smirkers</b></a>
<a><b>murkier</b></a>
<a><b>mirkest</b></a>
<a><b>murkiest</b></a>
<a><b>muskier</b></a>
<a><b>mikes</b></a>
<a><b>kismets</b></a>
<a><b>muskiest</b></a>
<a><b>muskies</b></a>
<a><b>kismet</b></a>
<a><b>muskie</b></a>
<a><b>kine</b></a>
<a><b>nonstrikers</b></a>
<a><b>nonstriker</b></a>
<a><b>knottiness</b></a>
</CATALOG>
