<?xml version="1.0" encoding="UTF-8"?>
<CATALOG>
<a><b>urbanologist</b></a>
<a><b>laboring</b></a>
<a><b>laborings</b></a>
<a><b>labouring</b></a>
<a><b>subtotaling</b></a>
<a><b>boastingly</b></a>
<a><b>absolving</b></a>
<a><b>bloating</b></a>
<a><b>blaring</b></a>
<a><b>brattling</b></a>
<a><b>warbling</b></a>
<a><b>brawling</b></a>
<a><b>ablings</b></a>
<a><b>blastings</b></a>
<a><b>stablings</b></a>
<a><b>blasting</b></a>
<a><b>stabling</b></a>
<a><b>tabling</b></a>
<a><b>blatting</b></a>
<a><b>battling</b></a>
<a><b>tangibly</b></a>
<a><b>bawling</b></a>
<a><b>blazing</b></a>
<a><b>astrobiology</b></a>
<a><b>obligator</b></a>
<a><b>obligatory</b></a>
<a><b>obligato</b></a>
<a><b>burglarious</b></a>
<a><b>mamboing</b></a>
<a><b>barnstorming</b></a>
<a><b>tambouring</b></a>
<a><b>unambiguous</b></a>
<a><b>rumbaing</b></a>
<a><b>bigamous</b></a>
<a><b>ambiguous</b></a>
<a><b>gambits</b></a>
<a><b>gambit</b></a>
<a><b>bigamy</b></a>
<a><b>banning</b></a>
<a><b>aborning</b></a>
<a><b>unbarring</b></a>
<a><b>banting</b></a>
<a><b>bagnio</b></a>
<a><b>bootstrapping</b></a>
<a><b>outboasting</b></a>
<a><b>tabooing</b></a>
<a><b>probating</b></a>
<a><b>aborting</b></a>
<a><b>bravoing</b></a>
<a><b>bagnios</b></a>
<a><b>boatings</b></a>
<a><b>boasting</b></a>
<a><b>boating</b></a>
<a><b>bypassing</b></a>
<a><b>baring</b></a>
<a><b>barring</b></a>
<a><b>sabring</b></a>
<a><b>braving</b></a>
<a><b>braying</b></a>
<a><b>brazing</b></a>
<a><b>basing</b></a>
<a><b>bastings</b></a>
<a><b>basting</b></a>
<a><b>battings</b></a>
<a><b>abusing</b></a>
<a><b>bating</b></a>
<a><b>batting</b></a>
<a><b>abutting</b></a>
<a><b>tabuing</b></a>
<a><b>batwing</b></a>
<a><b>baying</b></a>
<a><b>subjugators</b></a>
<a><b>subjugator</b></a>
<a><b>bangkok</b></a>
<a><b>bangkoks</b></a>
<a><b>workbags</b></a>
<a><b>workbag</b></a>
<a><b>globularly</b></a>
<a><b>globally</b></a>
<a><b>gullably</b></a>
<a><b>global</b></a>
<a><b>globular</b></a>
<a><b>bullyrags</b></a>
<a><b>bullyrag</b></a>
<a><b>gambol</b></a>
<a><b>gambols</b></a>
<a><b>lumbagos</b></a>
<a><b>lumbago</b></a>
<a><b>bologna</b></a>
<a><b>urbanology</b></a>
<a><b>bolognas</b></a>
<a><b>longboats</b></a>
<a><b>longboat</b></a>
<a><b>bungalows</b></a>
<a><b>bungalow</b></a>
<a><b>glabrous</b></a>
<a><b>burglars</b></a>
<a><b>burglar</b></a>
<a><b>burglary</b></a>
<a><b>boogyman</b></a>
</CATALOG>
