<?xml version="1.0" encoding="UTF-8"?>
<CATALOG>
<a><b>eliminating</b></a>
<a><b>alimenting</b></a>
<a><b>elating</b></a>
<a><b>guerrilla</b></a>
<a><b>allegro</b></a>
<a><b>allegros</b></a>
<a><b>allegory</b></a>
<a><b>allergy</b></a>
<a><b>gleam</b></a>
<a><b>gleams</b></a>
<a><b>gleamy</b></a>
<a><b>glean</b></a>
<a><b>gleans</b></a>
<a><b>areology</b></a>
<a><b>elapsing</b></a>
<a><b>alerting</b></a>
<a><b>smegma</b></a>
<a><b>smegmas</b></a>
<a><b>omega</b></a>
<a><b>omegas</b></a>
<a><b>eviscerating</b></a>
<a><b>enframing</b></a>
<a><b>engrailing</b></a>
<a><b>engraining</b></a>
<a><b>engraving</b></a>
<a><b>engravings</b></a>
<a><b>everlasting</b></a>
<a><b>etiolating</b></a>
<a><b>averring</b></a>
<a><b>gonorrhoea</b></a>
<a><b>gonorrhea</b></a>
<a><b>enervating</b></a>
<a><b>averting</b></a>
<a><b>anergy</b></a>
<a><b>anesthetizing</b></a>
<a><b>anesthesiology</b></a>
<a><b>esophagus</b></a>
<a><b>erasing</b></a>
<a><b>greats</b></a>
<a><b>greasy</b></a>
<a><b>great</b></a>
<a><b>greta</b></a>
<a><b>plexiglass</b></a>
<a><b>plexiglas</b></a>
<a><b>guffawing</b></a>
<a><b>guffaw</b></a>
<a><b>flagging</b></a>
<a><b>flaggings</b></a>
<a><b>fragging</b></a>
<a><b>fraggings</b></a>
<a><b>flaggy</b></a>
<a><b>flailing</b></a>
<a><b>flaking</b></a>
<a><b>franking</b></a>
<a><b>foaling</b></a>
<a><b>foaming</b></a>
<a><b>framing</b></a>
<a><b>flag</b></a>
<a><b>flanging</b></a>
<a><b>flashing</b></a>
<a><b>flashings</b></a>
<a><b>flanking</b></a>
<a><b>flamingly</b></a>
<a><b>flamming</b></a>
<a><b>flaming</b></a>
<a><b>flamingo</b></a>
<a><b>flamingos</b></a>
<a><b>flaunting</b></a>
<a><b>flaring</b></a>
<a><b>flawing</b></a>
<a><b>flaying</b></a>
<a><b>flauntingly</b></a>
<a><b>flapping</b></a>
<a><b>flatting</b></a>
<a><b>flagon</b></a>
<a><b>flavouring</b></a>
<a><b>flavoring</b></a>
<a><b>flagons</b></a>
<a><b>flags</b></a>
<a><b>engrafting</b></a>
<a><b>flashguns</b></a>
<a><b>flashgun</b></a>
<a><b>frapping</b></a>
<a><b>frag</b></a>
<a><b>argufying</b></a>
<a><b>fraying</b></a>
<a><b>frazzling</b></a>
<a><b>frags</b></a>
<a><b>frayings</b></a>
<a><b>flavorings</b></a>
<a><b>gag</b></a>
<a><b>cliffhanging</b></a>
<a><b>allergology</b></a>
<a><b>gaggling</b></a>
<a><b>gagging</b></a>
<a><b>gangling</b></a>
<a><b>gargling</b></a>
<a><b>gaging</b></a>
<a><b>ganging</b></a>
<a><b>gauging</b></a>
</CATALOG>
