<?xml version="1.0" encoding="UTF-8"?>
<CATALOG>
<a><b>bedizen</b></a>
<a><b>disobeyers</b></a>
<a><b>disobeyer</b></a>
<a><b>briquetted</b></a>
<a><b>berried</b></a>
<a><b>bestirred</b></a>
<a><b>riverbeds</b></a>
<a><b>retributed</b></a>
<a><b>reburied</b></a>
<a><b>riverbed</b></a>
<a><b>derbies</b></a>
<a><b>bestrides</b></a>
<a><b>birdseyes</b></a>
<a><b>bestride</b></a>
<a><b>birdseye</b></a>
<a><b>bittered</b></a>
<a><b>beside</b></a>
<a><b>besides</b></a>
<a><b>betides</b></a>
<a><b>bisexed</b></a>
<a><b>betide</b></a>
<a><b>debunkers</b></a>
<a><b>debunker</b></a>
<a><b>bunkered</b></a>
<a><b>unrebuked</b></a>
<a><b>overbooked</b></a>
<a><b>kerbed</b></a>
<a><b>rebuked</b></a>
<a><b>bleed</b></a>
<a><b>belled</b></a>
<a><b>underbelly</b></a>
<a><b>bowelled</b></a>
<a><b>bellowed</b></a>
<a><b>wellbred</b></a>
<a><b>blessedly</b></a>
<a><b>bullweeds</b></a>
<a><b>bulleted</b></a>
<a><b>bullweed</b></a>
<a><b>embolden</b></a>
<a><b>emboldens</b></a>
<a><b>slumbered</b></a>
<a><b>trembled</b></a>
<a><b>lumbered</b></a>
<a><b>umbeled</b></a>
<a><b>ennobled</b></a>
<a><b>boundlessness</b></a>
<a><b>doubleness</b></a>
<a><b>unbeloved</b></a>
<a><b>blender</b></a>
<a><b>blunderers</b></a>
<a><b>blunderer</b></a>
<a><b>blenders</b></a>
<a><b>unblessed</b></a>
<a><b>obsoleted</b></a>
<a><b>bolstered</b></a>
<a><b>redoubles</b></a>
<a><b>redouble</b></a>
<a><b>beloveds</b></a>
<a><b>beloved</b></a>
<a><b>elbowed</b></a>
<a><b>boweled</b></a>
<a><b>burlesqued</b></a>
<a><b>blustered</b></a>
<a><b>trebled</b></a>
<a><b>bleeds</b></a>
<a><b>blessed</b></a>
<a><b>debtless</b></a>
<a><b>belted</b></a>
<a><b>embed</b></a>
<a><b>embosomed</b></a>
<a><b>unnumbered</b></a>
<a><b>burdensome</b></a>
<a><b>outnumbered</b></a>
<a><b>entombed</b></a>
<a><b>numbered</b></a>
<a><b>emborders</b></a>
<a><b>reembody</b></a>
<a><b>embossed</b></a>
<a><b>bumpered</b></a>
<a><b>submersed</b></a>
<a><b>umbered</b></a>
<a><b>embeds</b></a>
<a><b>bemused</b></a>
<a><b>bonneted</b></a>
<a><b>debone</b></a>
<a><b>enrobed</b></a>
<a><b>overburdens</b></a>
<a><b>overburden</b></a>
<a><b>unobserved</b></a>
<a><b>rebuttoned</b></a>
<a><b>bowedness</b></a>
<a><b>prebend</b></a>
<a><b>unperturbed</b></a>
<a><b>prebends</b></a>
<a><b>bender</b></a>
<a><b>burdeners</b></a>
<a><b>burdener</b></a>
<a><b>benders</b></a>
<a><b>reprobed</b></a>
<a><b>proverbed</b></a>
</CATALOG>
