<?xml version="1.0" encoding="UTF-8"?>
<CATALOG>
<a><b>windshield</b></a>
<a><b>doodle</b></a>
<a><b>doodler</b></a>
<a><b>doodlers</b></a>
<a><b>doodles</b></a>
<a><b>elongated</b></a>
<a><b>linefeed</b></a>
<a><b>levelled</b></a>
<a><b>leveled</b></a>
<a><b>lessened</b></a>
<a><b>lettered</b></a>
<a><b>levered</b></a>
<a><b>leveed</b></a>
<a><b>weregild</b></a>
<a><b>lingered</b></a>
<a><b>wergeld</b></a>
<a><b>deservingly</b></a>
<a><b>dishevels</b></a>
<a><b>dishevel</b></a>
<a><b>liveried</b></a>
<a><b>livened</b></a>
<a><b>diversely</b></a>
<a><b>livered</b></a>
<a><b>levied</b></a>
<a><b>pommeled</b></a>
<a><b>unmelted</b></a>
<a><b>lengthened</b></a>
<a><b>divergently</b></a>
<a><b>lessoned</b></a>
<a><b>derisively</b></a>
<a><b>letted</b></a>
<a><b>elude</b></a>
<a><b>despiteful</b></a>
<a><b>fetidly</b></a>
<a><b>tenfold</b></a>
<a><b>slogged</b></a>
<a><b>wergild</b></a>
<a><b>unmingled</b></a>
<a><b>withheld</b></a>
<a><b>devilishly</b></a>
<a><b>dishonestly</b></a>
<a><b>threshold</b></a>
<a><b>dishtowels</b></a>
<a><b>dishtowel</b></a>
<a><b>lionhearted</b></a>
<a><b>leukemoid</b></a>
<a><b>littered</b></a>
<a><b>divisively</b></a>
<a><b>divinely</b></a>
<a><b>lionized</b></a>
<a><b>linked</b></a>
<a><b>dissolutely</b></a>
<a><b>limed</b></a>
<a><b>limitedly</b></a>
<a><b>limited</b></a>
<a><b>lined</b></a>
<a><b>disorderly</b></a>
<a><b>spoiled</b></a>
<a><b>despoil</b></a>
<a><b>despoils</b></a>
<a><b>deviously</b></a>
<a><b>lipped</b></a>
<a><b>dispel</b></a>
<a><b>lisped</b></a>
<a><b>dispels</b></a>
<a><b>direly</b></a>
<a><b>limiteds</b></a>
<a><b>disruptively</b></a>
<a><b>devil</b></a>
<a><b>lived</b></a>
<a><b>dewily</b></a>
<a><b>plonked</b></a>
<a><b>dell</b></a>
<a><b>pommelled</b></a>
<a><b>despitefully</b></a>
<a><b>polled</b></a>
<a><b>rolled</b></a>
<a><b>droller</b></a>
<a><b>drollery</b></a>
<a><b>drollest</b></a>
<a><b>trolled</b></a>
<a><b>tolled</b></a>
<a><b>polluted</b></a>
<a><b>dells</b></a>
<a><b>lewdly</b></a>
<a><b>delly</b></a>
<a><b>meld</b></a>
<a><b>demurely</b></a>
<a><b>limned</b></a>
<a><b>limped</b></a>
<a><b>remold</b></a>
<a><b>remolds</b></a>
<a><b>melody</b></a>
<a><b>melds</b></a>
<a><b>lend</b></a>
<a><b>dissidently</b></a>
<a><b>linseed</b></a>
<a><b>linseeds</b></a>
<a><b>lensed</b></a>
<a><b>densely</b></a>
</CATALOG>
