<?xml version="1.0" encoding="UTF-8"?>
<CATALOG>
<a><b>oppugn</b></a>
<a><b>popgun</b></a>
<a><b>prong</b></a>
<a><b>prongs</b></a>
<a><b>grownups</b></a>
<a><b>grownup</b></a>
<a><b>spongy</b></a>
<a><b>strong</b></a>
<a><b>wrongs</b></a>
<a><b>wrong</b></a>
<a><b>grown</b></a>
<a><b>nogs</b></a>
<a><b>song</b></a>
<a><b>songs</b></a>
<a><b>tongs</b></a>
<a><b>outguns</b></a>
<a><b>youngs</b></a>
<a><b>gowns</b></a>
<a><b>tong</b></a>
<a><b>ungot</b></a>
<a><b>outgun</b></a>
<a><b>young</b></a>
<a><b>gown</b></a>
<a><b>sprung</b></a>
<a><b>upswung</b></a>
<a><b>strung</b></a>
<a><b>grunts</b></a>
<a><b>rungs</b></a>
<a><b>grunt</b></a>
<a><b>rung</b></a>
<a><b>wrung</b></a>
<a><b>snugs</b></a>
<a><b>stung</b></a>
<a><b>sung</b></a>
<a><b>guns</b></a>
<a><b>gnus</b></a>
<a><b>snug</b></a>
<a><b>swung</b></a>
<a><b>gnu</b></a>
<a><b>gun</b></a>
<a><b>go</b></a>
<a><b>goo</b></a>
<a><b>goop</b></a>
<a><b>goops</b></a>
<a><b>grottos</b></a>
<a><b>outgrows</b></a>
<a><b>grotto</b></a>
<a><b>outgrow</b></a>
<a><b>groovy</b></a>
<a><b>goos</b></a>
<a><b>goosy</b></a>
<a><b>togo</b></a>
<a><b>outgo</b></a>
<a><b>progs</b></a>
<a><b>groups</b></a>
<a><b>group</b></a>
<a><b>porgy</b></a>
<a><b>turgors</b></a>
<a><b>gross</b></a>
<a><b>grots</b></a>
<a><b>rotguts</b></a>
<a><b>grouts</b></a>
<a><b>yogurts</b></a>
<a><b>grows</b></a>
<a><b>gorsy</b></a>
<a><b>gyros</b></a>
<a><b>grosz</b></a>
<a><b>grot</b></a>
<a><b>rotgut</b></a>
<a><b>grout</b></a>
<a><b>yogurt</b></a>
<a><b>grouty</b></a>
<a><b>grow</b></a>
<a><b>gory</b></a>
<a><b>gyro</b></a>
<a><b>orgy</b></a>
<a><b>togs</b></a>
<a><b>gouts</b></a>
<a><b>gusto</b></a>
<a><b>stogy</b></a>
<a><b>goys</b></a>
<a><b>tog</b></a>
<a><b>got</b></a>
<a><b>gout</b></a>
<a><b>gouty</b></a>
<a><b>govt</b></a>
<a><b>gov</b></a>
<a><b>goy</b></a>
<a><b>guppy</b></a>
<a><b>pugs</b></a>
<a><b>gyps</b></a>
<a><b>gypsy</b></a>
<a><b>pug</b></a>
<a><b>gyp</b></a>
<a><b>rugs</b></a>
<a><b>gurus</b></a>
<a><b>gyrus</b></a>
<a><b>surgy</b></a>
<a><b>rug</b></a>
<a><b>guru</b></a>
</CATALOG>
