<?xml version="1.0" encoding="UTF-8"?>
<CATALOG>
<a><b>hotly</b></a>
<a><b>howl</b></a>
<a><b>holy</b></a>
<a><b>plymouth</b></a>
<a><b>plush</b></a>
<a><b>plushy</b></a>
<a><b>hurl</b></a>
<a><b>hurly</b></a>
<a><b>loudmouths</b></a>
<a><b>plymouths</b></a>
<a><b>howls</b></a>
<a><b>slush</b></a>
<a><b>slushy</b></a>
<a><b>lush</b></a>
<a><b>logarithm</b></a>
<a><b>logarithms</b></a>
<a><b>mullah</b></a>
<a><b>moolah</b></a>
<a><b>moolahs</b></a>
<a><b>monograph</b></a>
<a><b>monographs</b></a>
<a><b>mynah</b></a>
<a><b>mobbish</b></a>
<a><b>monarch</b></a>
<a><b>monarchs</b></a>
<a><b>monarchy</b></a>
<a><b>inchworm</b></a>
<a><b>munich</b></a>
<a><b>inchworms</b></a>
<a><b>moloch</b></a>
<a><b>molochs</b></a>
<a><b>mulch</b></a>
<a><b>munch</b></a>
<a><b>munchy</b></a>
<a><b>mooch</b></a>
<a><b>much</b></a>
<a><b>mudfish</b></a>
<a><b>modish</b></a>
<a><b>moonlights</b></a>
<a><b>moonlight</b></a>
<a><b>moonfish</b></a>
<a><b>isomorphism</b></a>
<a><b>monkish</b></a>
<a><b>holmium</b></a>
<a><b>holmiums</b></a>
<a><b>holism</b></a>
<a><b>holisms</b></a>
<a><b>mulish</b></a>
<a><b>monolith</b></a>
<a><b>monoliths</b></a>
<a><b>moonish</b></a>
<a><b>monish</b></a>
<a><b>hypnotism</b></a>
<a><b>moorish</b></a>
<a><b>hookworm</b></a>
<a><b>hookworms</b></a>
<a><b>hokum</b></a>
<a><b>hokums</b></a>
<a><b>lunchroom</b></a>
<a><b>polymorph</b></a>
<a><b>homonym</b></a>
<a><b>homonymy</b></a>
<a><b>homonyms</b></a>
<a><b>moonshots</b></a>
<a><b>moonshot</b></a>
<a><b>month</b></a>
<a><b>months</b></a>
<a><b>hospitium</b></a>
<a><b>mopish</b></a>
<a><b>mushroom</b></a>
<a><b>homo</b></a>
<a><b>oomph</b></a>
<a><b>morpho</b></a>
<a><b>morphos</b></a>
<a><b>oomphs</b></a>
<a><b>homos</b></a>
<a><b>smooths</b></a>
<a><b>smooth</b></a>
<a><b>smoothy</b></a>
<a><b>morph</b></a>
<a><b>morphs</b></a>
<a><b>mouthwash</b></a>
<a><b>moth</b></a>
<a><b>mouth</b></a>
<a><b>mouthy</b></a>
<a><b>mothy</b></a>
<a><b>homy</b></a>
<a><b>mph</b></a>
<a><b>murphy</b></a>
<a><b>myrrh</b></a>
<a><b>isthmus</b></a>
<a><b>moths</b></a>
<a><b>mouths</b></a>
<a><b>mush</b></a>
<a><b>mushy</b></a>
<a><b>tmh</b></a>
<a><b>myth</b></a>
<a><b>hum</b></a>
<a><b>nomograph</b></a>
<a><b>nomography</b></a>
</CATALOG>
