<?xml version="1.0" encoding="UTF-8"?>
<CATALOG>
<a><b>monorails</b></a>
<a><b>moonily</b></a>
<a><b>moil</b></a>
<a><b>moils</b></a>
<a><b>moistly</b></a>
<a><b>multiply</b></a>
<a><b>trimly</b></a>
<a><b>multifariously</b></a>
<a><b>multitudinously</b></a>
<a><b>mussily</b></a>
<a><b>mustily</b></a>
<a><b>murkly</b></a>
<a><b>mutagenically</b></a>
<a><b>mutationally</b></a>
<a><b>municipally</b></a>
<a><b>musically</b></a>
<a><b>mythologically</b></a>
<a><b>monaurally</b></a>
<a><b>monastically</b></a>
<a><b>monochromatically</b></a>
<a><b>monopolistically</b></a>
<a><b>monophonically</b></a>
<a><b>monosyllabically</b></a>
<a><b>moll</b></a>
<a><b>myopically</b></a>
<a><b>monumentally</b></a>
<a><b>molls</b></a>
<a><b>molly</b></a>
<a><b>mystically</b></a>
<a><b>mutually</b></a>
<a><b>mull</b></a>
<a><b>monogamously</b></a>
<a><b>musicianly</b></a>
<a><b>unseemly</b></a>
<a><b>monotonously</b></a>
<a><b>monopoly</b></a>
<a><b>monstrously</b></a>
<a><b>moralistically</b></a>
<a><b>mothball</b></a>
<a><b>movably</b></a>
<a><b>morphological</b></a>
<a><b>mordantly</b></a>
<a><b>motional</b></a>
<a><b>morally</b></a>
<a><b>moral</b></a>
<a><b>morals</b></a>
<a><b>motivational</b></a>
<a><b>motivationally</b></a>
<a><b>moveably</b></a>
<a><b>morbidly</b></a>
<a><b>moribundly</b></a>
<a><b>murderously</b></a>
<a><b>motherly</b></a>
<a><b>motionlessly</b></a>
<a><b>morel</b></a>
<a><b>morosely</b></a>
<a><b>morels</b></a>
<a><b>motel</b></a>
<a><b>mouthful</b></a>
<a><b>mournful</b></a>
<a><b>mopingly</b></a>
<a><b>movingly</b></a>
<a><b>mopishly</b></a>
<a><b>mouthily</b></a>
<a><b>mousily</b></a>
<a><b>moronically</b></a>
<a><b>morphologically</b></a>
<a><b>mournfully</b></a>
<a><b>loom</b></a>
<a><b>pompously</b></a>
<a><b>looms</b></a>
<a><b>molto</b></a>
<a><b>mortally</b></a>
<a><b>mortal</b></a>
<a><b>morsel</b></a>
<a><b>morsels</b></a>
<a><b>mortifyingly</b></a>
<a><b>mortals</b></a>
<a><b>mysteriously</b></a>
<a><b>molts</b></a>
<a><b>mostly</b></a>
<a><b>molt</b></a>
<a><b>moly</b></a>
<a><b>lpm</b></a>
<a><b>posthumously</b></a>
<a><b>muscularly</b></a>
<a><b>lustrum</b></a>
<a><b>mothballs</b></a>
<a><b>motels</b></a>
<a><b>mutinously</b></a>
<a><b>mouthfuls</b></a>
<a><b>moults</b></a>
<a><b>moult</b></a>
<a><b>muzzily</b></a>
<a><b>nonclassical</b></a>
<a><b>nonchalantly</b></a>
<a><b>noneducational</b></a>
<a><b>nonagricultural</b></a>
<a><b>noncausal</b></a>
<a><b>noncasual</b></a>
</CATALOG>
