<?xml version="1.0" encoding="UTF-8"?>
<CATALOG>
<a><b>adjudicate</b></a>
<a><b>scandalized</b></a>
<a><b>quadruplicated</b></a>
<a><b>acidulated</b></a>
<a><b>candidatures</b></a>
<a><b>candidature</b></a>
<a><b>candidates</b></a>
<a><b>candidate</b></a>
<a><b>radicated</b></a>
<a><b>packsaddle</b></a>
<a><b>packsaddles</b></a>
<a><b>scandalled</b></a>
<a><b>landscaped</b></a>
<a><b>scandaled</b></a>
<a><b>placarded</b></a>
<a><b>cannonaded</b></a>
<a><b>advanced</b></a>
<a><b>advocated</b></a>
<a><b>arcaded</b></a>
<a><b>caudated</b></a>
<a><b>dandification</b></a>
<a><b>adjudicating</b></a>
<a><b>adjudications</b></a>
<a><b>adjudication</b></a>
<a><b>adjudicators</b></a>
<a><b>adjudicator</b></a>
<a><b>adjudicatory</b></a>
<a><b>radicands</b></a>
<a><b>autodidacts</b></a>
<a><b>autodidact</b></a>
<a><b>docudramas</b></a>
<a><b>docudrama</b></a>
<a><b>crawdads</b></a>
<a><b>crawdad</b></a>
<a><b>decaffeinates</b></a>
<a><b>decaffeinate</b></a>
<a><b>shamefacedness</b></a>
<a><b>preascertained</b></a>
<a><b>antecedental</b></a>
<a><b>deescalates</b></a>
<a><b>deescalate</b></a>
<a><b>decaffeinating</b></a>
<a><b>afterdischarge</b></a>
<a><b>shamefacedly</b></a>
<a><b>shamefaced</b></a>
<a><b>defalcates</b></a>
<a><b>defalcate</b></a>
<a><b>remanufactured</b></a>
<a><b>radiotelegraphic</b></a>
<a><b>casehardening</b></a>
<a><b>deescalating</b></a>
<a><b>undercarriages</b></a>
<a><b>undercarriage</b></a>
<a><b>prepackaged</b></a>
<a><b>repackaged</b></a>
<a><b>greatcoated</b></a>
<a><b>headache</b></a>
<a><b>hydrotherapeuticians</b></a>
<a><b>hydrotherapeutician</b></a>
<a><b>hydrotherapeutically</b></a>
<a><b>hydrotherapeutical</b></a>
<a><b>headachier</b></a>
<a><b>headaches</b></a>
<a><b>deathwatches</b></a>
<a><b>cardiotherapies</b></a>
<a><b>hexadecimal</b></a>
<a><b>echinodermata</b></a>
<a><b>archimedean</b></a>
<a><b>unauthenticated</b></a>
<a><b>authenticated</b></a>
<a><b>caseharden</b></a>
<a><b>casehardens</b></a>
<a><b>overattached</b></a>
<a><b>reattached</b></a>
<a><b>quadricentennials</b></a>
<a><b>quadricentennial</b></a>
<a><b>decentralizations</b></a>
<a><b>decentralization</b></a>
<a><b>denuclearization</b></a>
<a><b>undercapitalize</b></a>
<a><b>acetanilide</b></a>
<a><b>overcapitalized</b></a>
<a><b>recapitalized</b></a>
<a><b>americanized</b></a>
<a><b>inadequacies</b></a>
<a><b>pederastically</b></a>
<a><b>declaratively</b></a>
<a><b>uncompartmentalized</b></a>
<a><b>compartmentalized</b></a>
<a><b>transcendentalism</b></a>
<a><b>transcendentalizm</b></a>
<a><b>caramelized</b></a>
<a><b>transcendentalists</b></a>
<a><b>transcendentalist</b></a>
<a><b>deescalations</b></a>
<a><b>deescalation</b></a>
<a><b>intercalated</b></a>
<a><b>recapitulated</b></a>
<a><b>declarative</b></a>
<a><b>cavaliered</b></a>
</CATALOG>
