<?xml version="1.0" encoding="UTF-8"?>
<CATALOG>
<a><b>beacons</b></a>
<a><b>subcutaneous</b></a>
<a><b>buoyances</b></a>
<a><b>buoyance</b></a>
<a><b>cowbane</b></a>
<a><b>cranberry</b></a>
<a><b>canterbury</b></a>
<a><b>substances</b></a>
<a><b>substance</b></a>
<a><b>corroborates</b></a>
<a><b>corroborate</b></a>
<a><b>baroscope</b></a>
<a><b>caboose</b></a>
<a><b>cabooses</b></a>
<a><b>beaucoup</b></a>
<a><b>bracero</b></a>
<a><b>carburetors</b></a>
<a><b>carburetor</b></a>
<a><b>braceros</b></a>
<a><b>saucebox</b></a>
<a><b>subspace</b></a>
<a><b>acerb</b></a>
<a><b>brace</b></a>
<a><b>caber</b></a>
<a><b>bracer</b></a>
<a><b>bracers</b></a>
<a><b>carburets</b></a>
<a><b>cabers</b></a>
<a><b>braces</b></a>
<a><b>subraces</b></a>
<a><b>subrace</b></a>
<a><b>cubature</b></a>
<a><b>abscess</b></a>
<a><b>subcauses</b></a>
<a><b>subacute</b></a>
<a><b>backfiring</b></a>
<a><b>subclassifying</b></a>
<a><b>bifurcating</b></a>
<a><b>obfuscating</b></a>
<a><b>bifurcations</b></a>
<a><b>bifurcation</b></a>
<a><b>backfill</b></a>
<a><b>backfills</b></a>
<a><b>finbacks</b></a>
<a><b>bifocal</b></a>
<a><b>bifocals</b></a>
<a><b>subclassify</b></a>
<a><b>obfuscation</b></a>
<a><b>subfractions</b></a>
<a><b>subfraction</b></a>
<a><b>fabric</b></a>
<a><b>fabrics</b></a>
<a><b>fullbacks</b></a>
<a><b>fullback</b></a>
<a><b>blackfoot</b></a>
<a><b>softbacks</b></a>
<a><b>uncomfortably</b></a>
<a><b>conformably</b></a>
<a><b>comfortably</b></a>
<a><b>fluorocarbons</b></a>
<a><b>fluorocarbon</b></a>
<a><b>confab</b></a>
<a><b>confabs</b></a>
<a><b>obfuscators</b></a>
<a><b>obfuscator</b></a>
<a><b>obfuscatory</b></a>
<a><b>backlogging</b></a>
<a><b>piggybacks</b></a>
<a><b>piggyback</b></a>
<a><b>bushwhacking</b></a>
<a><b>charbroiling</b></a>
<a><b>cohabiting</b></a>
<a><b>biographic</b></a>
<a><b>blacklight</b></a>
<a><b>swashbuckling</b></a>
<a><b>thumbtacking</b></a>
<a><b>blanching</b></a>
<a><b>branching</b></a>
<a><b>branchings</b></a>
<a><b>broaching</b></a>
<a><b>batching</b></a>
<a><b>hogback</b></a>
<a><b>hogbacks</b></a>
<a><b>schoolbag</b></a>
<a><b>mistranscribing</b></a>
<a><b>bigamistic</b></a>
<a><b>blacklisting</b></a>
<a><b>bricklaying</b></a>
<a><b>bivouacking</b></a>
<a><b>biologically</b></a>
<a><b>bioclimatology</b></a>
<a><b>gnotobiotically</b></a>
<a><b>biological</b></a>
<a><b>lubricating</b></a>
<a><b>cabining</b></a>
<a><b>carbonizing</b></a>
<a><b>transcribing</b></a>
<a><b>incubating</b></a>
<a><b>carburizing</b></a>
<a><b>ascribing</b></a>
</CATALOG>
