<?xml version="1.0" encoding="UTF-8"?>
<CATALOG>
<a><b>brazening</b></a>
<a><b>absenting</b></a>
<a><b>battening</b></a>
<a><b>begonia</b></a>
<a><b>reprobating</b></a>
<a><b>begonias</b></a>
<a><b>bearing</b></a>
<a><b>bartering</b></a>
<a><b>bearings</b></a>
<a><b>sabering</b></a>
<a><b>breasting</b></a>
<a><b>berating</b></a>
<a><b>rebating</b></a>
<a><b>battering</b></a>
<a><b>betraying</b></a>
<a><b>bewaring</b></a>
<a><b>bassetting</b></a>
<a><b>beatings</b></a>
<a><b>beating</b></a>
<a><b>abetting</b></a>
<a><b>bagpipe</b></a>
<a><b>bagpiper</b></a>
<a><b>bagpipers</b></a>
<a><b>bagpipes</b></a>
<a><b>ribgrasses</b></a>
<a><b>objurgates</b></a>
<a><b>objurgate</b></a>
<a><b>subjugates</b></a>
<a><b>subjugate</b></a>
<a><b>bulkages</b></a>
<a><b>bulkage</b></a>
<a><b>brokage</b></a>
<a><b>brokages</b></a>
<a><b>grosbeak</b></a>
<a><b>grosbeaks</b></a>
<a><b>boskages</b></a>
<a><b>grubstaker</b></a>
<a><b>grubstakes</b></a>
<a><b>grubstake</b></a>
<a><b>bagel</b></a>
<a><b>gable</b></a>
<a><b>gleba</b></a>
<a><b>gullable</b></a>
<a><b>globularness</b></a>
<a><b>glassblowers</b></a>
<a><b>glassblower</b></a>
<a><b>gamble</b></a>
<a><b>gambrel</b></a>
<a><b>gambler</b></a>
<a><b>gamblers</b></a>
<a><b>gambles</b></a>
<a><b>mealybugs</b></a>
<a><b>mealybug</b></a>
<a><b>bangle</b></a>
<a><b>bengal</b></a>
<a><b>loganberry</b></a>
<a><b>gunbarrel</b></a>
<a><b>bengals</b></a>
<a><b>bangles</b></a>
<a><b>growable</b></a>
<a><b>globate</b></a>
<a><b>garble</b></a>
<a><b>garbler</b></a>
<a><b>garblers</b></a>
<a><b>garbles</b></a>
<a><b>garbless</b></a>
<a><b>bluegrass</b></a>
<a><b>bagels</b></a>
<a><b>gables</b></a>
<a><b>gustable</b></a>
<a><b>belugas</b></a>
<a><b>beluga</b></a>
<a><b>bagmen</b></a>
<a><b>boomerang</b></a>
<a><b>boomerangs</b></a>
<a><b>moneybags</b></a>
<a><b>bogeyman</b></a>
<a><b>moneybag</b></a>
<a><b>bergman</b></a>
<a><b>boomage</b></a>
<a><b>embargo</b></a>
<a><b>burgomasters</b></a>
<a><b>burgomaster</b></a>
<a><b>bergamots</b></a>
<a><b>umbrageous</b></a>
<a><b>bergamot</b></a>
<a><b>umbrages</b></a>
<a><b>umbrage</b></a>
<a><b>began</b></a>
<a><b>nosebag</b></a>
<a><b>nosebags</b></a>
<a><b>graben</b></a>
<a><b>banger</b></a>
<a><b>bangers</b></a>
<a><b>grabens</b></a>
<a><b>subagents</b></a>
<a><b>subagent</b></a>
<a><b>pageboys</b></a>
<a><b>pageboy</b></a>
<a><b>borage</b></a>
</CATALOG>
