<?xml version="1.0" encoding="UTF-8"?>
<CATALOG>
<a><b>aped</b></a>
<a><b>approbated</b></a>
<a><b>appreciated</b></a>
<a><b>appraised</b></a>
<a><b>appropriated</b></a>
<a><b>approximated</b></a>
<a><b>depreciative</b></a>
<a><b>depreciate</b></a>
<a><b>depreciates</b></a>
<a><b>deprecative</b></a>
<a><b>deprecate</b></a>
<a><b>deprecates</b></a>
<a><b>apprenticed</b></a>
<a><b>depreciated</b></a>
<a><b>deprecated</b></a>
<a><b>depredated</b></a>
<a><b>apprehended</b></a>
<a><b>depredate</b></a>
<a><b>depraved</b></a>
<a><b>depravedness</b></a>
<a><b>deprogrammed</b></a>
<a><b>depressionary</b></a>
<a><b>depraver</b></a>
<a><b>deprave</b></a>
<a><b>depravities</b></a>
<a><b>depraves</b></a>
<a><b>approached</b></a>
<a><b>polyhedra</b></a>
<a><b>deputative</b></a>
<a><b>apprised</b></a>
<a><b>apprized</b></a>
<a><b>deprogrammer</b></a>
<a><b>deprogrammers</b></a>
<a><b>approved</b></a>
<a><b>dapper</b></a>
<a><b>departs</b></a>
<a><b>depart</b></a>
<a><b>apostatized</b></a>
<a><b>apostrophized</b></a>
<a><b>adepts</b></a>
<a><b>adept</b></a>
<a><b>bequeathed</b></a>
<a><b>dear</b></a>
<a><b>dare</b></a>
<a><b>curtailed</b></a>
<a><b>curtained</b></a>
<a><b>dehydrator</b></a>
<a><b>certificated</b></a>
<a><b>argufied</b></a>
<a><b>dafter</b></a>
<a><b>argued</b></a>
<a><b>denunciatory</b></a>
<a><b>darwinite</b></a>
<a><b>editorializer</b></a>
<a><b>dietary</b></a>
<a><b>driveway</b></a>
<a><b>adjurer</b></a>
<a><b>adjuster</b></a>
<a><b>delusionary</b></a>
<a><b>medullar</b></a>
<a><b>medullary</b></a>
<a><b>danseurs</b></a>
<a><b>danseur</b></a>
<a><b>crosshatched</b></a>
<a><b>aroused</b></a>
<a><b>drear</b></a>
<a><b>darer</b></a>
<a><b>darers</b></a>
<a><b>redraws</b></a>
<a><b>darter</b></a>
<a><b>redraw</b></a>
<a><b>dreary</b></a>
<a><b>dears</b></a>
<a><b>dares</b></a>
<a><b>derats</b></a>
<a><b>derat</b></a>
<a><b>deary</b></a>
<a><b>deray</b></a>
<a><b>assuaged</b></a>
<a><b>denuclearizes</b></a>
<a><b>centerboards</b></a>
<a><b>adjudges</b></a>
<a><b>dehydrogenates</b></a>
<a><b>dehydrates</b></a>
<a><b>dehydrators</b></a>
<a><b>bestialized</b></a>
<a><b>daguerreotypes</b></a>
<a><b>deathlessness</b></a>
<a><b>deathless</b></a>
<a><b>yesterday</b></a>
<a><b>aestivated</b></a>
<a><b>daftness</b></a>
<a><b>daftest</b></a>
<a><b>dehumanizes</b></a>
<a><b>deaths</b></a>
<a><b>dietitians</b></a>
<a><b>editorializers</b></a>
<a><b>editorializes</b></a>
<a><b>editorialist</b></a>
<a><b>driveways</b></a>
</CATALOG>
