<?xml version="1.0" encoding="UTF-8"?>
<CATALOG>
<a><b>assimilable</b></a>
<a><b>alterable</b></a>
<a><b>apposable</b></a>
<a><b>bloater</b></a>
<a><b>bloaters</b></a>
<a><b>concealer</b></a>
<a><b>concealers</b></a>
<a><b>citadel</b></a>
<a><b>elucidate</b></a>
<a><b>confidentialness</b></a>
<a><b>discriminately</b></a>
<a><b>disconsolately</b></a>
<a><b>alnicoes</b></a>
<a><b>auricle</b></a>
<a><b>clodpate</b></a>
<a><b>alongside</b></a>
<a><b>altitude</b></a>
<a><b>alphabetize</b></a>
<a><b>alphabetizer</b></a>
<a><b>alphabetizers</b></a>
<a><b>alphabetizes</b></a>
<a><b>easeful</b></a>
<a><b>elongate</b></a>
<a><b>elongates</b></a>
<a><b>aerogels</b></a>
<a><b>heterosexual</b></a>
<a><b>heterosexually</b></a>
<a><b>generally</b></a>
<a><b>general</b></a>
<a><b>generals</b></a>
<a><b>aloneness</b></a>
<a><b>espanoles</b></a>
<a><b>earnestly</b></a>
<a><b>aureole</b></a>
<a><b>easel</b></a>
<a><b>easels</b></a>
<a><b>venezuela</b></a>
<a><b>feral</b></a>
<a><b>earful</b></a>
<a><b>earfuls</b></a>
<a><b>fetal</b></a>
<a><b>egomaniacal</b></a>
<a><b>genially</b></a>
<a><b>germinal</b></a>
<a><b>genial</b></a>
<a><b>genal</b></a>
<a><b>genital</b></a>
<a><b>egoistically</b></a>
<a><b>egoistical</b></a>
<a><b>genitals</b></a>
<a><b>almightiness</b></a>
<a><b>alongshore</b></a>
<a><b>hernial</b></a>
<a><b>lethally</b></a>
<a><b>lethal</b></a>
<a><b>armhole</b></a>
<a><b>armholes</b></a>
<a><b>asshole</b></a>
<a><b>hesitantly</b></a>
<a><b>dispassionately</b></a>
<a><b>disparately</b></a>
<a><b>automobile</b></a>
<a><b>leukemia</b></a>
<a><b>aerofoil</b></a>
<a><b>aerofoils</b></a>
<a><b>aluminize</b></a>
<a><b>lineally</b></a>
<a><b>literally</b></a>
<a><b>aimlessly</b></a>
<a><b>lineal</b></a>
<a><b>alpinely</b></a>
<a><b>linearly</b></a>
<a><b>airlessly</b></a>
<a><b>literal</b></a>
<a><b>lineman</b></a>
<a><b>alumine</b></a>
<a><b>linesman</b></a>
<a><b>alpine</b></a>
<a><b>alpines</b></a>
<a><b>peninsulas</b></a>
<a><b>peninsula</b></a>
<a><b>linear</b></a>
<a><b>peninsular</b></a>
<a><b>disproportionately</b></a>
<a><b>aerily</b></a>
<a><b>dissuasively</b></a>
<a><b>easily</b></a>
<a><b>leukoma</b></a>
<a><b>leal</b></a>
<a><b>egomaniacally</b></a>
<a><b>allen</b></a>
<a><b>leanly</b></a>
<a><b>allotrope</b></a>
<a><b>aller</b></a>
<a><b>allotter</b></a>
<a><b>allover</b></a>
<a><b>alertly</b></a>
<a><b>allure</b></a>
<a><b>allotropes</b></a>
<a><b>allovers</b></a>
</CATALOG>
