<?xml version="1.0" encoding="UTF-8"?>
<CATALOG>
<a><b>innocent</b></a>
<a><b>continent</b></a>
<a><b>connie</b></a>
<a><b>noncorrosive</b></a>
<a><b>counterpoints</b></a>
<a><b>nonprecious</b></a>
<a><b>counterpoint</b></a>
<a><b>nonpoetic</b></a>
<a><b>connoisseurs</b></a>
<a><b>connoisseur</b></a>
<a><b>conversions</b></a>
<a><b>conversion</b></a>
<a><b>contentious</b></a>
<a><b>encryptions</b></a>
<a><b>princeton</b></a>
<a><b>encryption</b></a>
<a><b>corniness</b></a>
<a><b>continuers</b></a>
<a><b>centurions</b></a>
<a><b>connivers</b></a>
<a><b>uncontrite</b></a>
<a><b>intercounty</b></a>
<a><b>continuer</b></a>
<a><b>centurion</b></a>
<a><b>neuronic</b></a>
<a><b>conniver</b></a>
<a><b>connivery</b></a>
<a><b>consistent</b></a>
<a><b>constituents</b></a>
<a><b>constituent</b></a>
<a><b>continues</b></a>
<a><b>connives</b></a>
<a><b>continue</b></a>
<a><b>connive</b></a>
<a><b>quincunxes</b></a>
<a><b>vincent</b></a>
<a><b>procession</b></a>
<a><b>processions</b></a>
<a><b>prosecutions</b></a>
<a><b>prosecution</b></a>
<a><b>retinoscopy</b></a>
<a><b>protection</b></a>
<a><b>copiousness</b></a>
<a><b>totipotency</b></a>
<a><b>censorious</b></a>
<a><b>cortisone</b></a>
<a><b>contortive</b></a>
<a><b>neurotoxic</b></a>
<a><b>porcupines</b></a>
<a><b>porcupine</b></a>
<a><b>porcine</b></a>
<a><b>conspirer</b></a>
<a><b>conspirers</b></a>
<a><b>conspire</b></a>
<a><b>conspires</b></a>
<a><b>percussions</b></a>
<a><b>supersonics</b></a>
<a><b>inspectors</b></a>
<a><b>percussion</b></a>
<a><b>supersonic</b></a>
<a><b>inceptors</b></a>
<a><b>inspector</b></a>
<a><b>provinces</b></a>
<a><b>province</b></a>
<a><b>pectinous</b></a>
<a><b>nepotic</b></a>
<a><b>unpoetic</b></a>
<a><b>recoin</b></a>
<a><b>coiner</b></a>
<a><b>cornier</b></a>
<a><b>cursoriness</b></a>
<a><b>tricornes</b></a>
<a><b>contrivers</b></a>
<a><b>coinsurer</b></a>
<a><b>tricorne</b></a>
<a><b>contriver</b></a>
<a><b>incretory</b></a>
<a><b>recoins</b></a>
<a><b>cronies</b></a>
<a><b>coiners</b></a>
<a><b>necrosis</b></a>
<a><b>curiousness</b></a>
<a><b>cornetists</b></a>
<a><b>coinsures</b></a>
<a><b>excursions</b></a>
<a><b>corniest</b></a>
<a><b>cornetist</b></a>
<a><b>neurotics</b></a>
<a><b>countries</b></a>
<a><b>cretinous</b></a>
<a><b>contrives</b></a>
<a><b>excursion</b></a>
<a><b>contrite</b></a>
<a><b>neurotic</b></a>
<a><b>contrive</b></a>
<a><b>corvine</b></a>
<a><b>conies</b></a>
<a><b>cosine</b></a>
<a><b>cosines</b></a>
<a><b>cession</b></a>
</CATALOG>
