<?xml version="1.0" encoding="UTF-8"?>
<CATALOG>
<a><b>nonentities</b></a>
<a><b>insentient</b></a>
<a><b>interspersions</b></a>
<a><b>interspersion</b></a>
<a><b>reinsertion</b></a>
<a><b>intersessions</b></a>
<a><b>intersession</b></a>
<a><b>overinsistent</b></a>
<a><b>inventories</b></a>
<a><b>prizewinners</b></a>
<a><b>prizewinner</b></a>
<a><b>spinneries</b></a>
<a><b>intrusiveness</b></a>
<a><b>intertwines</b></a>
<a><b>intertwine</b></a>
<a><b>intestines</b></a>
<a><b>unsensitive</b></a>
<a><b>intensives</b></a>
<a><b>einstein</b></a>
<a><b>nineties</b></a>
<a><b>intestine</b></a>
<a><b>intensive</b></a>
<a><b>inventive</b></a>
<a><b>onerosities</b></a>
<a><b>notorieties</b></a>
<a><b>propensities</b></a>
<a><b>surreptitiousness</b></a>
<a><b>expressionists</b></a>
<a><b>expressionist</b></a>
<a><b>petitioners</b></a>
<a><b>repetitions</b></a>
<a><b>repetition</b></a>
<a><b>petitioner</b></a>
<a><b>positiveness</b></a>
<a><b>reversionist</b></a>
<a><b>introversive</b></a>
<a><b>nervosities</b></a>
<a><b>venosities</b></a>
<a><b>interruptive</b></a>
<a><b>pineries</b></a>
<a><b>viperine</b></a>
<a><b>enquiries</b></a>
<a><b>winterier</b></a>
<a><b>riverine</b></a>
<a><b>investitures</b></a>
<a><b>neuritises</b></a>
<a><b>interties</b></a>
<a><b>enteritis</b></a>
<a><b>investiture</b></a>
<a><b>winteriest</b></a>
<a><b>reinvites</b></a>
<a><b>interviews</b></a>
<a><b>winterizes</b></a>
<a><b>vineries</b></a>
<a><b>inversive</b></a>
<a><b>wineries</b></a>
<a><b>reinvite</b></a>
<a><b>interview</b></a>
<a><b>winterize</b></a>
<a><b>veinier</b></a>
<a><b>sensitizes</b></a>
<a><b>tensities</b></a>
<a><b>sensitive</b></a>
<a><b>sensitize</b></a>
<a><b>entities</b></a>
<a><b>invitees</b></a>
<a><b>wienies</b></a>
<a><b>invitee</b></a>
<a><b>wienie</b></a>
<a><b>repositories</b></a>
<a><b>proprieties</b></a>
<a><b>equipoises</b></a>
<a><b>equipoise</b></a>
<a><b>posterities</b></a>
<a><b>repetitious</b></a>
<a><b>territories</b></a>
<a><b>rotisseries</b></a>
<a><b>rotisserie</b></a>
<a><b>sovietizes</b></a>
<a><b>sovietize</b></a>
<a><b>perquisites</b></a>
<a><b>perquisite</b></a>
<a><b>expiries</b></a>
<a><b>pieties</b></a>
<a><b>requisites</b></a>
<a><b>requisite</b></a>
<a><b>equities</b></a>
<a><b>exquisite</b></a>
<a><b>resistive</b></a>
<a><b>restitutive</b></a>
<a><b>verities</b></a>
<a><b>viewier</b></a>
<a><b>jellylike</b></a>
<a><b>jerkiness</b></a>
<a><b>jerkier</b></a>
<a><b>jerkies</b></a>
<a><b>jerkiest</b></a>
<a><b>jellies</b></a>
<a><b>juliennes</b></a>
<a><b>julienne</b></a>
</CATALOG>
