<?xml version="1.0" encoding="UTF-8"?>
<CATALOG>
<a><b>shells</b></a>
<a><b>shelly</b></a>
<a><b>helm</b></a>
<a><b>menthols</b></a>
<a><b>menthol</b></a>
<a><b>unhelm</b></a>
<a><b>wormholes</b></a>
<a><b>wormhole</b></a>
<a><b>lothsome</b></a>
<a><b>phloem</b></a>
<a><b>humorless</b></a>
<a><b>motherly</b></a>
<a><b>holmes</b></a>
<a><b>homely</b></a>
<a><b>helms</b></a>
<a><b>methyls</b></a>
<a><b>whelms</b></a>
<a><b>methyl</b></a>
<a><b>whelm</b></a>
<a><b>xylophones</b></a>
<a><b>xylophone</b></a>
<a><b>honorless</b></a>
<a><b>holystones</b></a>
<a><b>holystone</b></a>
<a><b>phenol</b></a>
<a><b>phenols</b></a>
<a><b>northerly</b></a>
<a><b>hornless</b></a>
<a><b>honestly</b></a>
<a><b>lushness</b></a>
<a><b>tenthly</b></a>
<a><b>huntley</b></a>
<a><b>hole</b></a>
<a><b>portholes</b></a>
<a><b>porthole</b></a>
<a><b>hoopless</b></a>
<a><b>postholes</b></a>
<a><b>potholes</b></a>
<a><b>posthole</b></a>
<a><b>holotypes</b></a>
<a><b>pothole</b></a>
<a><b>toothless</b></a>
<a><b>upholsters</b></a>
<a><b>upholster</b></a>
<a><b>upholstery</b></a>
<a><b>sploshes</b></a>
<a><b>phloxes</b></a>
<a><b>holer</b></a>
<a><b>throttlers</b></a>
<a><b>throttler</b></a>
<a><b>hostlers</b></a>
<a><b>holsters</b></a>
<a><b>throstles</b></a>
<a><b>worthless</b></a>
<a><b>hostler</b></a>
<a><b>holster</b></a>
<a><b>throstle</b></a>
<a><b>throttles</b></a>
<a><b>southerly</b></a>
<a><b>hostelry</b></a>
<a><b>howlers</b></a>
<a><b>throttle</b></a>
<a><b>whortle</b></a>
<a><b>helotry</b></a>
<a><b>howler</b></a>
<a><b>sheol</b></a>
<a><b>holes</b></a>
<a><b>sheols</b></a>
<a><b>sloshes</b></a>
<a><b>hostels</b></a>
<a><b>shovels</b></a>
<a><b>helots</b></a>
<a><b>hotels</b></a>
<a><b>tholes</b></a>
<a><b>hostel</b></a>
<a><b>shovel</b></a>
<a><b>hovels</b></a>
<a><b>wholes</b></a>
<a><b>hoyles</b></a>
<a><b>thole</b></a>
<a><b>helot</b></a>
<a><b>hotel</b></a>
<a><b>howlet</b></a>
<a><b>hovel</b></a>
<a><b>whole</b></a>
<a><b>hoyle</b></a>
<a><b>holey</b></a>
<a><b>help</b></a>
<a><b>plusher</b></a>
<a><b>helps</b></a>
<a><b>shlep</b></a>
<a><b>plushest</b></a>
<a><b>plushes</b></a>
<a><b>whelps</b></a>
<a><b>whelp</b></a>
<a><b>hurlers</b></a>
<a><b>hurler</b></a>
<a><b>truthless</b></a>
<a><b>hurtless</b></a>
<a><b>hustlers</b></a>
<a><b>ruthless</b></a>
</CATALOG>
