<?xml version="1.0" encoding="UTF-8"?>
<CATALOG>
<a><b>introduces</b></a>
<a><b>intrenches</b></a>
<a><b>invoices</b></a>
<a><b>involucres</b></a>
<a><b>intricateness</b></a>
<a><b>ontogenies</b></a>
<a><b>inurements</b></a>
<a><b>enuresis</b></a>
<a><b>involvements</b></a>
<a><b>intriguers</b></a>
<a><b>intrigues</b></a>
<a><b>ontologies</b></a>
<a><b>entomologists</b></a>
<a><b>entomologist</b></a>
<a><b>slushiness</b></a>
<a><b>nitrites</b></a>
<a><b>involuntariness</b></a>
<a><b>invokers</b></a>
<a><b>invokes</b></a>
<a><b>kittens</b></a>
<a><b>involutes</b></a>
<a><b>involves</b></a>
<a><b>involvers</b></a>
<a><b>mittens</b></a>
<a><b>mizzens</b></a>
<a><b>intoners</b></a>
<a><b>environs</b></a>
<a><b>intones</b></a>
<a><b>introspectiveness</b></a>
<a><b>inventors</b></a>
<a><b>interns</b></a>
<a><b>introversions</b></a>
<a><b>intents</b></a>
<a><b>invents</b></a>
<a><b>invertors</b></a>
<a><b>introverts</b></a>
<a><b>envious</b></a>
<a><b>envois</b></a>
<a><b>interrupts</b></a>
<a><b>investors</b></a>
<a><b>nitres</b></a>
<a><b>niters</b></a>
<a><b>inters</b></a>
<a><b>inverts</b></a>
<a><b>inures</b></a>
<a><b>invests</b></a>
<a><b>intoxicates</b></a>
<a><b>intruders</b></a>
<a><b>intrudes</b></a>
<a><b>intrusiveness</b></a>
<a><b>nixes</b></a>
<a><b>intravenous</b></a>
<a><b>housesits</b></a>
<a><b>potpies</b></a>
<a><b>soviets</b></a>
<a><b>pluralities</b></a>
<a><b>pluralizes</b></a>
<a><b>pourboires</b></a>
<a><b>potteries</b></a>
<a><b>plutocracies</b></a>
<a><b>potsies</b></a>
<a><b>potties</b></a>
<a><b>spurries</b></a>
<a><b>pixes</b></a>
<a><b>squires</b></a>
<a><b>squire</b></a>
<a><b>routinizes</b></a>
<a><b>jitters</b></a>
<a><b>litters</b></a>
<a><b>rivers</b></a>
<a><b>rites</b></a>
<a><b>rivets</b></a>
<a><b>rives</b></a>
<a><b>sixties</b></a>
<a><b>skywrites</b></a>
<a><b>sizzles</b></a>
<a><b>smuttiness</b></a>
<a><b>issues</b></a>
<a><b>sites</b></a>
<a><b>tissue</b></a>
<a><b>tissuey</b></a>
<a><b>sixtes</b></a>
<a><b>issue</b></a>
<a><b>sixes</b></a>
<a><b>sizes</b></a>
<a><b>site</b></a>
<a><b>intuitiveness</b></a>
<a><b>intwines</b></a>
<a><b>ritziness</b></a>
<a><b>ritziest</b></a>
<a><b>skywrite</b></a>
<a><b>rivulets</b></a>
<a><b>entwists</b></a>
<a><b>entwist</b></a>
<a><b>ritzes</b></a>
<a><b>sixte</b></a>
<a><b>vise</b></a>
<a><b>wise</b></a>
<a><b>size</b></a>
<a><b>tie</b></a>
</CATALOG>
